chissl/__init__.py
chissl/_version.py
chissl/chissl.py
chissl/react_jupyter_widget.py
chissl/static/extension.js
chissl/static/index.js
chissl/static/index.js.map
chissl-0.1.0b0.data/data/etc/jupyter/nbconfig/notebook.d/chissl-widget.json
chissl-0.1.0b0.data/data/share/jupyter/nbextensions/chissl-widget/extension.js
chissl-0.1.0b0.data/data/share/jupyter/nbextensions/chissl-widget/index.js
chissl-0.1.0b0.data/data/share/jupyter/nbextensions/chissl-widget/index.js.map
chissl-0.1.0b0.dist-info/METADATA
chissl-0.1.0b0.dist-info/WHEEL
chissl-0.1.0b0.dist-info/top_level.txt
chissl-0.1.0b0.dist-info/RECORD
